sphinxtools
