Metadata-Version: 1.0
Name: sphinxtools
Version: 0.2
Summary: Paver tasks for Sphinx Search server
Home-page: https://github.com/jpvanhal/sphinxtools
Author: Janne Vanhala
Author-email: janne.vanhala@gmail.com
License: New BSD License
Keywords: paver sphinxsearch
Platform: UNKNOWN
Classifier: Development Status :: 3 - Alpha
Classifier: Environment :: Console
Classifier: Intended Audience :: Developers
Classifier: License :: OSI Approved :: BSD License
Classifier: Operating System :: OS Independent
Classifier: Programming Language :: Python
Classifier: Topic :: Internet :: WWW/HTTP :: Indexing/Search
Classifier: Topic :: Software Development
